setup.py
bluelens_log/__init__.py
bluelens_log/logging.py
bluelens_log.egg-info/PKG-INFO
bluelens_log.egg-info/SOURCES.txt
bluelens_log.egg-info/dependency_links.txt
bluelens_log.egg-info/requires.txt
bluelens_log.egg-info/top_level.txt