Metadata-Version: 1.0
Name: bluelens-log
Version: 1.0.2
Summary: bluelens-log
Home-page: UNKNOWN
Author: UNKNOWN
Author-email: master@bluehack.net
License: UNKNOWN
Keywords: bluelens,bluelens-log
Platform: UNKNOWN
